csv_embeddings_creator.py
csv_embeddings_creator-1.0.9.dist-info/METADATA
csv_embeddings_creator-1.0.9.dist-info/WHEEL
csv_embeddings_creator-1.0.9.dist-info/entry_points.txt
csv_embeddings_creator-1.0.9.dist-info/top_level.txt
csv_embeddings_creator-1.0.9.dist-info/RECORD
