Metadata-Version: 2.1
Name: csv-embeddings-creator
Version: 1.0.9
Requires-Dist: torch
Requires-Dist: sentence-transformers
Requires-Dist: argparse
